myTest.py
maoTest-1.0.dist-info/METADATA
maoTest-1.0.dist-info/WHEEL
maoTest-1.0.dist-info/top_level.txt
maoTest-1.0.dist-info/RECORD
