Metadata-Version: 2.1
Name: maoTest
Version: 1.0
Summary: A module for test
Home-page: UNKNOWN
Author: Mao Haotian
Author-email: 404748294@qq.com
License: MIT
Platform: UNKNOWN
